<?xml version="1.0" encoding="utf-8" ?>
<dwsync>
<file name="index.html" server="passionfruit.dothome.co.kr" local="132979711200000000" remote="132979711200000000" Dst="0" />
<file name="index2.html" server="passionfruit.dothome.co.kr" local="132966970200000000" remote="132966970200000000" Dst="0" />
<file name="index3.html" server="passionfruit.dothome.co.kr" local="132966970200000000" remote="132966970200000000" Dst="0" />
<file name="style.css" server="passionfruit.dothome.co.kr" local="132950613810366773" remote="132950289600000000" Dst="0" />
<file name="파비콘.png" server="passionfruit.dothome.co.kr" local="132937789586122976" remote="132937467000000000" Dst="0" />
<file name="setup-finish.html" server="passionfruit.dothome.co.kr" local="132336828000000000" remote="132336828000000000" Dst="0" />
<file name="login.html" server="passionfruit.dothome.co.kr" local="132979711200000000" remote="132979711200000000" Dst="0" />
<file name="insert.php" server="passionfruit.dothome.co.kr" local="132938565862830345" remote="132938241600000000" Dst="0" />
<file name="favicon.ico" server="passionfruit.dothome.co.kr" local="132938415600000000" remote="132938415600000000" Dst="0" />
<file name="main.html" server="passionfruit.dothome.co.kr" local="132979711200000000" remote="132979711200000000" Dst="0" />
<file name="jquery-3.3.1.min.js" server="passionfruit.dothome.co.kr" local="131802961240000000" remote="132944439600000000" Dst="0" />
<file name="swiper.min.css" server="passionfruit.dothome.co.kr" local="131833832540000000" remote="132944439600000000" Dst="0" />
<file name="swiper.min.js" server="passionfruit.dothome.co.kr" local="131813599160000000" remote="132944439600000000" Dst="0" />
<file name="img.zip" server="passionfruit.dothome.co.kr" local="132945762965024080" remote="132947086800000000" Dst="0" />
<file name="index4.html" server="passionfruit.dothome.co.kr" local="132966970200000000" remote="132966970200000000" Dst="0" />
<file name="index5.html" server="passionfruit.dothome.co.kr" local="132966969000000000" remote="132966969000000000" Dst="0" />
</dwsync>